dsinfluxlogger/__init__.py
dsinfluxlogger/console.py
dsinfluxlogger/defaultconfig.py
dsinfluxlogger/py.typed
dsinfluxlogger/service.py
dsinfluxlogger-0.5.0.dist-info/entry_points.txt
dsinfluxlogger-0.5.0.dist-info/LICENSE
dsinfluxlogger-0.5.0.dist-info/WHEEL
dsinfluxlogger-0.5.0.dist-info/METADATA
dsinfluxlogger-0.5.0.dist-info/RECORD
