Metadata-Version: 2.1
Name: dsinfluxlogger
Version: 0.5.0
Summary: Log datamessages to influxdb
Home-page: https://gitlab.com/advian-oss/python-dsinfluxlogger/
License: MIT
Author: Eero af Heurlin
Author-email: eero.afheurlin@iki.fi
Requires-Python: >=3.8,<4.0
Classifier: License :: OSI Approved :: MIT License
Classifier: Programming Language :: Python :: 3
Classifier: Programming Language :: Python :: 3.8
Classifier: Programming Language :: Python :: 3.9
Requires-Dist: aioinflux (>=0.9,<0.10)
Requires-Dist: datastreamservicelib (>=1.10,<2.0)
Requires-Dist: flatten-dict (>=0.3,<0.4)
Project-URL: Repository, https://gitlab.com/advian-oss/python-dsinfluxlogger/
